truecasingIT/__init__.py
truecasingIT/punct.txt
truecasingIT/truecase.py
truecasingIT/wordforms.txt
truecasingIT-1.0.6.dist-info/METADATA
truecasingIT-1.0.6.dist-info/WHEEL
truecasingIT-1.0.6.dist-info/top_level.txt
truecasingIT-1.0.6.dist-info/RECORD
